nzpy/__init__.py
nzpy/_version.py
nzpy/core.py
nzpy/handshake.py
nzpy/numeric.py
nzpy-1.17.1.dist-info/licenses/LICENSE
nzpy-1.17.1.dist-info/METADATA
nzpy-1.17.1.dist-info/WHEEL
nzpy-1.17.1.dist-info/top_level.txt
nzpy-1.17.1.dist-info/RECORD
