Metadata-Version: 2.4
Name: nzpy
Version: 1.17.1
Summary: IBM Netezza python driver
Home-page: https://github.com/ibm/nzpy
Author: IBM
Author-email: shabmoh3@in.ibm.com
License: IBM
Project-URL: Documentation, https://github.com/IBM/nzpy/wiki
Project-URL: Source, https://github.com/IBM/nzpy
Project-URL: Tracker, https://github.com/IBM/nzpy/issues
Keywords: Netezza dbapi
Classifier: Development Status :: 5 - Production/Stable
Classifier: Intended Audience :: Developers
Classifier: License :: OSI Approved :: BSD License
Classifier: Programming Language :: Python
Classifier: Programming Language :: Python :: 3
Classifier: Programming Language :: Python :: 3.5
Classifier: Programming Language :: Python :: 3.6
Classifier: Programming Language :: Python :: Implementation
Classifier: Programming Language :: Python :: Implementation :: CPython
Classifier: Programming Language :: Python :: Implementation :: Jython
Classifier: Programming Language :: Python :: Implementation :: PyPy
Classifier: Operating System :: OS Independent
Classifier: Topic :: Database :: Front-Ends
Classifier: Topic :: Software Development :: Libraries :: Python Modules
Requires-Python: >=3.5
License-File: LICENSE
Requires-Dist: scramp==1.4.5
Requires-Dist: looseversion==1.3.0
Dynamic: author
Dynamic: author-email
Dynamic: classifier
Dynamic: description
Dynamic: description-content-type
Dynamic: home-page
Dynamic: keywords
Dynamic: license
Dynamic: license-file
Dynamic: project-url
Dynamic: requires-dist
Dynamic: requires-python
Dynamic: summary
